pytest_allure_host/__init__.py
pytest_allure_host/__main__.py
pytest_allure_host/_assets/dashboard/assets/runs-polish.css
pytest_allure_host/_assets/dashboard/assets/runtime.js
pytest_allure_host/_assets/dashboard/index.html
pytest_allure_host/cli.py
pytest_allure_host/config.py
pytest_allure_host/infra_cli.py
pytest_allure_host/plugin.py
pytest_allure_host/publisher.py
pytest_allure_host/templates.py
pytest_allure_host/utils.py
pytest_allure_host-2.1.8.dist-info/METADATA
pytest_allure_host-2.1.8.dist-info/WHEEL
pytest_allure_host-2.1.8.dist-info/entry_points.txt
pytest_allure_host-2.1.8.dist-info/licenses/LICENSE
pytest_allure_host-2.1.8.dist-info/RECORD
