Metadata-Version: 2.4
Name: pytest-allure-host
Version: 2.1.8
Summary: Publish Allure static reports to private S3 behind CloudFront with history preservation
License-Expression: MIT
License-File: LICENSE
Keywords: allure,pytest,aws,s3,cloudfront,reporting
Author: Allure Hosting Maintainers
Requires-Python: >=3.9,<4.0
Classifier: Programming Language :: Python :: 3
Classifier: Programming Language :: Python :: 3.9
Classifier: Programming Language :: Python :: 3.10
Classifier: Programming Language :: Python :: 3.11
Classifier: Programming Language :: Python :: 3.12
Classifier: Programming Language :: Python :: 3.13
Classifier: Intended Audience :: Developers
Classifier: Topic :: Software Development :: Testing
Classifier: Framework :: Pytest
Classifier: Development Status :: 3 - Alpha
Classifier: Operating System :: OS Independent
Requires-Dist: PyYAML (>=6,<7)
Requires-Dist: boto3 (>=1.28,<2.0)
Requires-Dist: python-dateutil (>=2.8.2,<3.0)
Requires-Dist: six (>=1.16,<2.0)
Project-URL: Bug Tracker, https://github.com/darrenrabbs/allurehosting/issues
Project-URL: Changelog, https://darrenrabbs.github.io/allurehosting/changelog/
Project-URL: Documentation, https://darrenrabbs.github.io/allurehosting/
Project-URL: Homepage, https://github.com/darrenrabbs/allurehosting
Project-URL: Repository, https://github.com/darrenrabbs/allurehosting
